MANIFEST.in
README.txt
setup.py
inv_content_list/__init__.py
inv_content_list/content_list.py
inv_content_list.egg-info/PKG-INFO
inv_content_list.egg-info/SOURCES.txt
inv_content_list.egg-info/dependency_links.txt
inv_content_list.egg-info/requires.txt
inv_content_list.egg-info/top_level.txt
inv_content_list/templates/content_list_style1.html
inv_content_list/templates/content_list_style2.html