Metadata-Version: 1.1
Name: inv-content-list
Version: 1.4
Summary: A random test lib11
Home-page: https://github.com/peterldowns/mypackage
Author: Eric Chu
Author-email: eric.chu@investopedia.com
License: UNKNOWN
Download-URL: https://github.com/peterldowns/mypackage/archive/0.1.tar.gz
Keywords: testing,logging,example
Platform: UNKNOWN
